[{"title": "Forest Fire", "id": 25503, "desc": null, "author": "Jhoper", "genre": [], "platform": ["Browser"]}, {"title": "Randome Adventures", "id": 31219, "desc": null, "author": "PixlePlays", "genre": [], "platform": ["Windows"]}, {"title": "NoMonstersYet! Windows", "id": 34331, "desc": "LudumDare #33 game", "author": "grieloliveira", "genre": [], "platform": ["Windows", "macOS"]}, {"title": "Go! Platform", "id": 43771, "desc": null, "author": "lldol10", "genre": [], "platform": ["Browser"]}, {"title": "\u00dajfaud\u00e9iscLvl02", "id": 45923, "desc": null, "author": "Caesar B. Frost", "genre": [], "platform": ["Browser"]}, {"title": "Mighty Mighty Cell", "id": 46846, "desc": null, "author": "Jhoper", "genre": [], "platform": ["Browser"]}, {"title": "The Biginig", "id": 50872, "desc": null, "author": "Black Assassin", "genre": [], "platform": []}, {"title": "Mixtape Adventures V2", "id": 57916, "desc": null, "author": "DavidSantos", "genre": [], "platform": ["Browser"]}, {"title": "locoman", "id": 58790, "desc": "es locoman que quieres que te diga", "author": "pabloman", "genre": [], "platform": ["Windows"]}, {"title": "Super Hyper Extreme Pizza Force 2", "id": 58870, "desc": null, "author": "Gerard Gilmartin", "genre": [], "platform": []}, {"title": "GET THERE!", "id": 60588, "desc": null, "author": "alexbat0311", "genre": [], "platform": []}, {"title": "Just One Jump", "id": 61612, "desc": "Just One Pit -  Just One Jump", "author": "Kertis Jones", "genre": [], "platform": []}, {"title": "Final Project V.1", "id": 64650, "desc": null, "author": "khalil franklin", "genre": [], "platform": ["Browser"]}, {"title": "Looping Game", "id": 64782, "desc": null, "author": "dvlanker", "genre": [], "platform": ["Browser"]}, {"title": "Khloie's Adventure", "id": 90015, "desc": "NOT FINISHED EVEN A LITTLE BIT AND PROBABLY WON'T WORK", "author": "mouldyport", "genre": [], "platform": ["Browser"]}, {"title": "flippityFlip", "id": 97798, "desc": "it's just flip the monkey", "author": "Radams5000", "genre": [], "platform": ["Browser"]}, {"title": "Accul's Revenge", "id": 98427, "desc": null, "author": "Studio Monera", "genre": [], "platform": ["Browser"]}, {"title": "Pixextra", "id": 106020, "desc": null, "author": "Quigley", "genre": [], "platform": ["Browser"]}, {"title": "WTBD Platformer", "id": 229160, "desc": "WTBD Platformer - 90% of sales goes to charity.", "author": "Fundacja WTBD", "genre": [], "platform": ["Windows"]}, {"title": "Cool Square Parkour", "id": 229721, "desc": "A work in progress parkour game!", "author": "Che3syPlays", "genre": [], "platform": ["Windows"]}, {"title": "Legend of the Three Amulets", "id": 259722, "desc": null, "author": "Master Krepta", "genre": [], "platform": ["Windows"]}, {"title": "GrayMars Adventure", "id": 287545, "desc": null, "author": "mertwole", "genre": [], "platform": ["Windows"]}, {"title": "Gravitron", "id": 315522, "desc": null, "author": "adrenator", "genre": [], "platform": []}, {"title": "Grumball Machine Madness", "id": 316069, "desc": "\"Help all the Grumballs escape the Destructo Corp factory before it blows up!\"", "author": "Guillermo Gee", "genre": [], "platform": ["Windows"]}, {"title": "S&N Bros", "id": 316635, "desc": null, "author": "AaronFan", "genre": [], "platform": ["Browser"]}, {"title": "Bridge Maker", "id": 359059, "desc": "Build bridges to cross platforms. Aim for perfect and obtain diamonds.", "author": "SK_27", "genre": [], "platform": ["Android"]}, {"title": "Horus", "id": 412395, "desc": null, "author": "Kevin Chuang", "genre": [], "platform": ["Browser"]}, {"title": "Hopeless", "id": 420955, "desc": "Platforming Game", "author": "Seeker13", "genre": [], "platform": ["Windows"]}, {"title": "Distancy", "id": 423723, "desc": "Life is hard!", "author": "CubbyCrazes", "genre": [], "platform": ["Windows"]}, {"title": "Moon Boy", "id": 433132, "desc": null, "author": "Green Origami", "genre": [], "platform": []}]