[{"title": "Hot Dog Roller", "id": 21794, "desc": null, "author": "Felipe Nanni", "genre": [], "platform": ["Browser"]}, {"title": "2015KusoGame", "id": 29358, "desc": "gamejam", "author": "killer767", "genre": [], "platform": ["Browser"]}, {"title": "Attack on White Man", "id": 33207, "desc": "Watch out Aaron Yeahger", "author": "FakeLemon", "genre": [], "platform": ["Browser"]}, {"title": "Dodgy-Ball", "id": 40949, "desc": "One Game-a-Week #2", "author": "chongdashu", "genre": [], "platform": ["Browser"]}, {"title": "Bowling with Words", "id": 45765, "desc": null, "author": "DizzyHeights", "genre": [], "platform": []}, {"title": "Midterm Project Pong v1.1", "id": 57870, "desc": "pong with a twist", "author": "khalil franklin", "genre": [], "platform": ["Browser"]}, {"title": "Midterm Project Final Iteration", "id": 59415, "desc": null, "author": "khalil franklin", "genre": [], "platform": ["Browser"]}, {"title": "Dawn of the Arrow", "id": 62825, "desc": "Two player twin stick target shooting game", "author": "SeanBrady", "genre": [], "platform": ["Windows", "macOS"]}, {"title": "Autochase", "id": 66802, "desc": null, "author": "galacticgaming", "genre": [], "platform": ["Browser"]}, {"title": "Pongity V0.01", "id": 84084, "desc": "Pong against yourself in a best of three!", "author": "Reverend Speed", "genre": [], "platform": ["Browser"]}, {"title": "StarShot", "id": 87685, "desc": null, "author": "RaymondNg", "genre": [], "platform": []}, {"title": "Major League Dodgecube", "id": 90718, "desc": "Two player cube-dodging game", "author": "Adrian Randy Satrianugraha", "genre": [], "platform": ["macOS"]}, {"title": "Bullseye", "id": 92049, "desc": "Try to shoot as close to the center as you can!", "author": "Stratubas", "genre": [], "platform": ["Windows"]}, {"title": "Star Race", "id": 108618, "desc": "Rogue One made me do this.", "author": "akumarai", "genre": [], "platform": ["Browser"]}, {"title": "PYRAMID FALLS", "id": 112407, "desc": "Smash those blocks!", "author": "Dynamic Soul Works", "genre": [], "platform": ["Windows"]}, {"title": "test", "id": 117891, "desc": null, "author": "qli1", "genre": [], "platform": ["Browser"]}, {"title": "Top Pool", "id": 126169, "desc": null, "author": "mention", "genre": [], "platform": ["Android"]}, {"title": "QB arcade", "id": 147464, "desc": null, "author": "wtrsltnk", "genre": [], "platform": ["Windows", "Android"]}, {"title": "Race to the Castle [alpha]", "id": 167872, "desc": null, "author": "Bhumit Chaudhry", "genre": [], "platform": ["Windows", "macOS"]}, {"title": "HUNGRY HANDS", "id": 174432, "desc": null, "author": "Baileyfit", "genre": [], "platform": ["Browser"]}, {"title": "StickDodgeVR: VR dodge ball for the HTC VIVE", "id": 185239, "desc": "StickDodgeVR", "author": "The StickDodgeVR Team", "genre": [], "platform": ["Windows"]}, {"title": "Ultimate Catch!", "id": 190316, "desc": null, "author": "Applefruit", "genre": [], "platform": []}, {"title": "pong-8", "id": 238019, "desc": "Classic Pong clone implemented in PICO-8", "author": "baraujo42", "genre": [], "platform": ["Browser"]}, {"title": "Oliver the Torchbearer", "id": 248119, "desc": "\u200bJoin Oliver, a relatively young tree person, in his once in a lifetime opportunity to deliver the Oleampian Flame.", "author": "Fachewachewa", "genre": [], "platform": ["Windows"]}, {"title": "Bungee Stars", "id": 252363, "desc": "Bungee your way to as many stars as you can.", "author": "Jayenkai", "genre": [], "platform": ["Windows", "Linux", "macOS"]}, {"title": "Dionysus Drinking Darts", "id": 285304, "desc": "Drink wine, play darts!", "author": "4sight", "genre": [], "platform": ["Browser"]}, {"title": "Mini pong", "id": 314803, "desc": null, "author": "gildevs", "genre": [], "platform": ["Browser"]}, {"title": "Simple Pong", "id": 315592, "desc": null, "author": "Maksym Postument", "genre": [], "platform": ["Browser"]}, {"title": "Unibot Ball Random Ballspawn Test", "id": 317403, "desc": "Testing of randomised color and location on ballspawn", "author": "Aquatic Llama", "genre": [], "platform": ["Browser"]}, {"title": "Soccer Rocketball League Champions:Hyperball Games", "id": 411070, "desc": "Want to play car socer game with concept of hyper 3D ball and Car Wars 2019?", "author": "Gameseller76", "genre": [], "platform": []}]