[{"title": "Il Cammino Delle Capre - The Goat Path", "id": 17513, "desc": null, "author": "Kris Mukai", "genre": [], "platform": []}, {"title": "[encrypted]", "id": 25454, "desc": "A short-form abstract roguelike.", "author": "Niall Moody", "genre": [], "platform": ["Windows", "macOS"]}, {"title": "An Open Field", "id": 27615, "desc": "essay + game meditating on death, mortality and memories", "author": "Ansh", "genre": [], "platform": ["Windows"]}, {"title": "Predestination", "id": 31148, "desc": "Multiple beginnings but one ending. A small branching narrative about three women.", "author": "Mighty CheBo", "genre": [], "platform": ["Windows"]}, {"title": "Zine Fair Lady", "id": 33304, "desc": "a game about small publications and microagressions", "author": "MorganSea", "genre": [], "platform": ["Browser"]}, {"title": "Sex Life", "id": 58512, "desc": "Enjoy university and don't get pregnant.", "author": "Rosa Carbo-Mascarell", "genre": [], "platform": ["Windows"]}, {"title": "Nervs.", "id": 60530, "desc": "A very short game about anxiety.", "author": "ell0", "genre": [], "platform": ["macOS"]}, {"title": "Temporary Friends Vol1", "id": 78443, "desc": "Short twine zine of thoughts", "author": "communistsister", "genre": [], "platform": ["Browser"]}, {"title": "L\u2019Origine du Monde", "id": 101029, "desc": "(NSFW) Mini game remembering a trip to the Mus\u00e9e d\u2019Orsay in Paris", "author": "boysunday", "genre": [], "platform": ["Windows", "Linux", "macOS"]}, {"title": "Avocado Smash", "id": 101651, "desc": "Brunch Satire", "author": "shallow_depths", "genre": [], "platform": ["Windows", "Linux", "macOS"]}, {"title": "EVERYTHING IS GOING TO BE OK", "id": 116158, "desc": "EVERYTHING IS GOING TO BE OK is a nihilistic horror comedy zine-game about life", "author": "alienmelon", "genre": [], "platform": ["Windows", "macOS"]}, {"title": "DYSTROPICANA", "id": 116516, "desc": "multimedia archipelago", "author": "AAA", "genre": [], "platform": ["Windows"]}, {"title": "Halseny Issue #1", "id": 118080, "desc": "A combination of science fiction and fantasy awaits you in this issue!", "author": "halseny", "genre": [], "platform": []}, {"title": "SJW: Digital Zine Quest", "id": 126919, "desc": "Are you a Social Justice Warrior? Or are you more of a Social Justice Druid? Or Summoner?", "author": "Nathan Blades", "genre": [], "platform": ["Browser"]}, {"title": "Humaning", "id": 129340, "desc": "An interspecies tabletop RPG", "author": "Kara Stone", "genre": [], "platform": []}, {"title": "no mutants here", "id": 145851, "desc": "answer the door a dozen ways", "author": "Kit", "genre": [], "platform": ["Windows"]}, {"title": "The Zium Museum (2017)", "id": 188760, "desc": "Enter The Zium Museum", "author": "The Zium Museum", "genre": [], "platform": ["Windows", "Linux", "macOS"]}, {"title": "Whimsy.Space", "id": 190219, "desc": "A retro-futuristic operating-system experience!", "author": "Daniel X Moore", "genre": [], "platform": ["Browser"]}, {"title": "c i r c u i t s", "id": 205260, "desc": "a narrative journey through remembering, witnessing, and trauma", "author": "Eileen Mary Holowka", "genre": [], "platform": ["Browser"]}, {"title": "NEMESISTERS", "id": 266674, "desc": "An infinite galaxy of sisters. A finite father's love to monopolize.", "author": "Ryan Wolf", "genre": [], "platform": ["Browser"]}, {"title": "What a treat to hear Thy Word", "id": 273021, "desc": "A Bitsy game of my thoughts on Cathedrals.", "author": "Richard Sherriff", "genre": [], "platform": ["Browser"]}, {"title": "Love Me Not", "id": 286876, "desc": "Love me, Love me not", "author": "Max", "genre": [], "platform": ["Browser"]}, {"title": "words are seeds", "id": 350752, "desc": "\u200blet your words become tree's", "author": "Max", "genre": [], "platform": ["Browser"]}, {"title": "Sailor Moon Popsicle", "id": 370341, "desc": "Scattered thoughts on identity.", "author": "asteroidskeeper", "genre": [], "platform": ["Browser"]}, {"title": "Psycle: a choose-your-own-therapy zine session", "id": 380573, "desc": "a mental health journey in dance", "author": "B. Zolaire", "genre": [], "platform": ["Browser"]}, {"title": "this year i've been", "id": 393817, "desc": "short interactive poem about being alive and taking care of yourself", "author": "brie_irl", "genre": [], "platform": ["Windows", "Linux", "Android"]}, {"title": "I Didn't Work On My Game", "id": 423238, "desc": "Here's what I did instead.", "author": "andimlenny", "genre": [], "platform": []}, {"title": "Mornings", "id": 427586, "desc": "Interactive Zine about Mornings", "author": "itsNemo", "genre": [], "platform": ["Browser"]}, {"title": "Baga\u00e7o", "id": 428773, "desc": "someone thought that a game was a good way of expressing feelings", "author": "lawendt", "genre": [], "platform": ["Windows"]}, {"title": "The Summit", "id": 432273, "desc": "The summit awaits you.", "author": "itsNemo", "genre": [], "platform": []}]